README.md
setup.py
grpc_web/__init__.py
grpc_web.egg-info/PKG-INFO
grpc_web.egg-info/SOURCES.txt
grpc_web.egg-info/dependency_links.txt
grpc_web.egg-info/not-zip-safe
grpc_web.egg-info/top_level.txt