Metadata-Version: 2.1
Name: grpc-web
Version: 0.0.0
Summary: gRPC Web
Home-page: UNKNOWN
License: MIT
Keywords: grpc-web
Platform: UNKNOWN
Classifier: Development Status :: 1 - Planning
Classifier: Intended Audience :: Developers
Classifier: License :: OSI Approved :: MIT License
Classifier: Programming Language :: Python :: 3
Classifier: Topic :: Software Development
Classifier: Topic :: Software Development :: Libraries
Classifier: Topic :: Software Development :: Libraries :: Python Modules
